# synchronized

**这是一个Synchronized几种用法的java类：**

```java
public class SyncTest {

    public synchronized void methodOne() {

    }

    public void methodTwo() {
        synchronized (this) {
        }
    }

    public synchronized static void methodThree() {

    }
}
```

将上面的SyncTest 编译成class文件

```
javac SyncTest.java
```

class文件我们是不能直接进行观看的，得把他编译成字节码文件

我们通过这个命令：

```
javap -v SyncTest.class
```

**编译好的字节码文件了：**

```java
{
  public com.bilibili.itlaoge.juc.SyncTest();
    descriptor: ()V
    flags: ACC_PUBLIC
    Code:
      stack=1, locals=1, args_size=1
         0: aload_0
         1: invokespecial #1                  // Method java/lang/Object."<init>":()V
         4: return
      LineNumberTable:
        line 3: 0

  public synchronized void methodOne();
    descriptor: ()V
    flags: ACC_PUBLIC, ACC_SYNCHRONIZED // 同步锁的关键
    Code:
      stack=0, locals=1, args_size=1
         0: return
      LineNumberTable:
        line 7: 0

  public void methodTwo();
    descriptor: ()V
    flags: ACC_PUBLIC
    Code:
      stack=2, locals=3, args_size=1
         0: aload_0
         1: dup
         2: astore_1
         3: monitorenter // 进入锁
         4: aload_1
         5: monitorexit // 释放锁
         6: goto          14
         9: astore_2
        10: aload_1
        11: monitorexit // 保证在发生异常的情况下，也能正常的释放锁
        12: aload_2
        13: athrow
        14: return
      Exception table:
         from    to  target type
             4     6     9   any
             9    12     9   any
      LineNumberTable:
        line 10: 0
        line 11: 4
        line 12: 14
      StackMapTable: number_of_entries = 2
        frame_type = 255 /* full_frame */
          offset_delta = 9
          locals = [ class com/bilibili/itlaoge/juc/SyncTest, class java/lang/Object ]
          stack = [ class java/lang/Throwable ]
        frame_type = 250 /* chop */
          offset_delta = 4

  public static synchronized void methodThree();
    descriptor: ()V
    flags: ACC_PUBLIC, ACC_STATIC, ACC_SYNCHRONIZED // 同步锁的关键
    Code:
      stack=0, locals=0, args_size=0
         0: return
      LineNumberTable:
        line 16: 0
}
```

**ps：**从反编译的结果来看，方法的同步并没有通过指令monitorenter和monitorexit来完成（理论上其实也可以通过这两条指令来实现），不过相对于普通方法，其常量池中多了ACC_SYNCHRONIZED标示符。JVM就是根据该标示符来实现方法的同步的：当方法调用时，调用指令将会检查方法的 ACC_SYNCHRONIZED 访问标志是否被设置，如果设置了，执行线程将先获取monitor，获取成功之后才能执行方法体，方法执行完后再释放monitor。在方法执行期间，其他任何线程都无法再获得同一个monitor对象。其实本质上没有区别，只是方法的同步是一种隐式的方式来实现，无需通过字节码来完成。

**从官网找到jvm关于monitorenter 的一个描述如下：**

```
Each object is associated with a monitor. A monitor is locked if and only if it has an owner. The thread that executes monitorenter attempts to gain ownership of the monitor associated with objectref, as follows:
• If the entry count of the monitor associated with objectref is zero, the thread enters the monitor and sets its entry count to one. The thread is then the owner of the monitor.
• If the thread already owns the monitor associated with objectref, it reenters the monitor, incrementing its entry count.
• If another thread already owns the monitor associated with objectref, the thread blocks until the monitor's entry count is zero, then tries again to gain ownership.
```

**大概意思是：**  

每个对象有一个监视器锁（monitor）。当monitor被占用时就会处于锁定状态，线程执行monitorenter指令时尝试获取monitor的所有权，过程如下：

1、如果monitor的进入数为0，则该线程进入monitor，然后将进入数设置为1，该线程即为monitor的所有者。

2、如果线程已经占有该monitor，只是重新进入，则进入monitor的进入数加1.

3、如果其他线程已经占用了monitor，则该线程进入阻塞状态，直到monitor的进入数为0，再重新尝试获取monitor的所有权。



**monitorexit：**

```
thread that executes monitorexit must be the owner of the monitor associated with the instance referenced by objectref.
The thread decrements the entry count of the monitor associated with objectref. If as a result the value of the entry count is zero, the thread exits the monitor and is no longer its owner. Other threads that are blocking to enter the monitor are allowed to attempt to do so.
```

**这段话的大概意思为：**

执行monitorexit的线程必须是objectref所对应的monitor的所有者。

指令执行时，monitor的进入数减1，如果减1后进入数为0，那线程退出monitor，不再是这个monitor的所有者。其他被这个monitor阻塞的线程可以尝试去获取这个 monitor 的所有权。 

**一般来说monitorexit指令会有两个，但两个monitorexit不会都被执行，正常退出执行一个，异常中止执行另一个。**

通过这两段描述，我们应该能很清楚的看出Synchronized的实现原理，Synchronized的语义底层是通过一个monitor的对象来完成，其实wait/notify等方法也依赖于monitor对象，这就是为什么只有在同步的块或者方法中才能调用wait/notify等方法，否则会抛出java.lang.IllegalMonitorStateException的异常的原因。



## java源码层级

synchronized(o) 

## 字节码层级

monitorenter moniterexit

## JVM层级（Hotspot）

```java
package com.mashibing.insidesync;

import org.openjdk.jol.info.ClassLayout;

public class T01_Sync1 {
  

    public static void main(String[] args) {
        Object o = new Object();

        System.out.println(ClassLayout.parseInstance(o).toPrintable());
    }
}
```

```java
com.mashibing.insidesync.T01_Sync1$Lock object internals:
 OFFSET  SIZE   TYPE DESCRIPTION                               VALUE
      0     4   (object header)  05 00 00 00 (00000101 00000000 00000000 00000000) (5)
      4     4   (object header)  00 00 00 00 (00000000 00000000 00000000 00000000) (0)
      8     4   (object header)  49 ce 00 20 (01001001 11001110 00000000 00100000) (536923721)
     12     4        (loss due to the next object alignment)
Instance size: 16 bytes
Space losses: 0 bytes internal + 4 bytes external = 4 bytes total
```

```java
com.mashibing.insidesync.T02_Sync2$Lock object internals:
 OFFSET  SIZE   TYPE DESCRIPTION                               VALUE
      0     4   (object header)  05 90 2e 1e (00000101 10010000 00101110 00011110) (506368005)
      4     4   (object header)  1b 02 00 00 (00011011 00000010 00000000 00000000) (539)
      8     4   (object header)  49 ce 00 20 (01001001 11001110 00000000 00100000) (536923721)
     12     4        (loss due to the next object alignment)
Instance size: 16 bytes
Space losses: 0 bytes internal + 4 bytes external = 4 bytes tota
```

InterpreterRuntime:: monitorenter方法

```c++
IRT_ENTRY_NO_ASYNC(void, InterpreterRuntime::monitorenter(JavaThread* thread, BasicObjectLock* elem))
#ifdef ASSERT
  thread->last_frame().interpreter_frame_verify_monitor(elem);
#endif
  if (PrintBiasedLockingStatistics) {
    Atomic::inc(BiasedLocking::slow_path_entry_count_addr());
  }
  Handle h_obj(thread, elem->obj());
  assert(Universe::heap()->is_in_reserved_or_null(h_obj()),
         "must be NULL or an object");
  if (UseBiasedLocking) {
    // Retry fast entry if bias is revoked to avoid unnecessary inflation
    ObjectSynchronizer::fast_enter(h_obj, elem->lock(), true, CHECK);
  } else {
    ObjectSynchronizer::slow_enter(h_obj, elem->lock(), CHECK);
  }
  assert(Universe::heap()->is_in_reserved_or_null(elem->obj()),
         "must be NULL or an object");
#ifdef ASSERT
  thread->last_frame().interpreter_frame_verify_monitor(elem);
#endif
IRT_END
```

synchronizer.cpp

revoke_and_rebias

```c++
void ObjectSynchronizer::fast_enter(Handle obj, BasicLock* lock, bool attempt_rebias, TRAPS) {
 if (UseBiasedLocking) {
    if (!SafepointSynchronize::is_at_safepoint()) {
      BiasedLocking::Condition cond = BiasedLocking::revoke_and_rebias(obj, attempt_rebias, THREAD);
      if (cond == BiasedLocking::BIAS_REVOKED_AND_REBIASED) {
        return;
      }
    } else {
      assert(!attempt_rebias, "can not rebias toward VM thread");
      BiasedLocking::revoke_at_safepoint(obj);
    }
    assert(!obj->mark()->has_bias_pattern(), "biases should be revoked by now");
 }

 slow_enter (obj, lock, THREAD) ;
}
```

```c++
void ObjectSynchronizer::slow_enter(Handle obj, BasicLock* lock, TRAPS) {
  markOop mark = obj->mark();
  assert(!mark->has_bias_pattern(), "should not see bias pattern here");

  if (mark->is_neutral()) {
    // Anticipate successful CAS -- the ST of the displaced mark must
    // be visible <= the ST performed by the CAS.
    lock->set_displaced_header(mark);
    if (mark == (markOop) Atomic::cmpxchg_ptr(lock, obj()->mark_addr(), mark)) {
      TEVENT (slow_enter: release stacklock) ;
      return ;
    }
    // Fall through to inflate() ...
  } else
  if (mark->has_locker() && THREAD->is_lock_owned((address)mark->locker())) {
    assert(lock != mark->locker(), "must not re-lock the same lock");
    assert(lock != (BasicLock*)obj->mark(), "don't relock with same BasicLock");
    lock->set_displaced_header(NULL);
    return;
  }

#if 0
  // The following optimization isn't particularly useful.
  if (mark->has_monitor() && mark->monitor()->is_entered(THREAD)) {
    lock->set_displaced_header (NULL) ;
    return ;
  }
#endif

  // The object header will never be displaced to this lock,
  // so it does not matter what the value is, except that it
  // must be non-zero to avoid looking like a re-entrant lock,
  // and must not look locked either.
  lock->set_displaced_header(markOopDesc::unused_mark());
  ObjectSynchronizer::inflate(THREAD, obj())->enter(THREAD);
}
```

inflate方法：膨胀为重量级锁